onmt/__init__.py
onmt/constants.py
onmt/inference_engine.py
onmt/model_builder.py
onmt/opts.py
onmt/train_single.py
onmt/trainer.py
onmt/bin/__init__.py
onmt/bin/average_models.py
onmt/bin/build_vocab.py
onmt/bin/release_model.py
onmt/bin/server.py
onmt/bin/train.py
onmt/bin/translate.py
onmt/decoders/__init__.py
onmt/decoders/cnn_decoder.py
onmt/decoders/decoder.py
onmt/decoders/ensemble.py
onmt/decoders/transformer.py
onmt/encoders/__init__.py
onmt/encoders/cnn_encoder.py
onmt/encoders/encoder.py
onmt/encoders/ggnn_encoder.py
onmt/encoders/mean_encoder.py
onmt/encoders/rnn_encoder.py
onmt/encoders/transformer.py
onmt/inputters/__init__.py
onmt/inputters/dynamic_iterator.py
onmt/inputters/inputter.py
onmt/inputters/text_corpus.py
onmt/inputters/text_utils.py
onmt/models/__init__.py
onmt/models/model.py
onmt/models/model_saver.py
onmt/modules/__init__.py
onmt/modules/alibi_position_bias.py
onmt/modules/average_attn.py
onmt/modules/awq_linear.py
onmt/modules/bnb_linear.py
onmt/modules/conv_multi_step_attention.py
onmt/modules/copy_generator.py
onmt/modules/embeddings.py
onmt/modules/gate.py
onmt/modules/global_attention.py
onmt/modules/lora.py
onmt/modules/moe.py
onmt/modules/multi_headed_attn.py
onmt/modules/position_ffn.py
onmt/modules/rmsnorm.py
onmt/modules/sparse_activations.py
onmt/modules/sparse_losses.py
onmt/modules/sru.py
onmt/modules/stacked_rnn.py
onmt/modules/structured_attention.py
onmt/modules/util_class.py
onmt/modules/weight_norm.py
onmt/scorers/__init__.py
onmt/scorers/bleu.py
onmt/scorers/scorer.py
onmt/scorers/ter.py
onmt/tests/__init__.py
onmt/tests/test_attention.py
onmt/tests/test_beam_search.py
onmt/tests/test_copy_generator.py
onmt/tests/test_data_prepare.py
onmt/tests/test_embeddings.py
onmt/tests/test_events.py
onmt/tests/test_greedy_search.py
onmt/tests/test_inference_engines.py
onmt/tests/test_models.py
onmt/tests/test_simple.py
onmt/tests/test_structured_attention.py
onmt/tests/test_subword_marker.py
onmt/tests/test_text_utils.py
OpenNMT_py-3.5.1.dist-info/LICENSE.md
OpenNMT_py-3.5.1.dist-info/METADATA
OpenNMT_py-3.5.1.dist-info/WHEEL
OpenNMT_py-3.5.1.dist-info/entry_points.txt
OpenNMT_py-3.5.1.dist-info/top_level.txt
OpenNMT_py-3.5.1.dist-info/RECORD
