Metadata-Version: 2.1
Name: OpenNMT-py
Version: 3.5.1
Summary: A python implementation of OpenNMT
Project-URL: Documentation, http://opennmt.net/OpenNMT-py/
Project-URL: Forum, http://forum.opennmt.net/
Project-URL: Gitter, https://gitter.im/OpenNMT/OpenNMT-py
Project-URL: Source, https://github.com/OpenNMT/OpenNMT-py/
Requires-Python: >=3.9
License-File: LICENSE.md
Requires-Dist: torch <2.3,>=2.1
Requires-Dist: configargparse
Requires-Dist: ctranslate2 <5,>=4
Requires-Dist: tensorboard >=2.3
Requires-Dist: flask
Requires-Dist: waitress
Requires-Dist: pyonmttok <2,>=1.37
Requires-Dist: pyyaml
Requires-Dist: sacrebleu
Requires-Dist: rapidfuzz
Requires-Dist: pyahocorasick
Requires-Dist: fasttext-wheel
Requires-Dist: spacy
Requires-Dist: six
